arztalep/__init__.py
arztalep/arztalep.py
arztalepkutuphanesi/__init__.py
arztalepkutuphanesi/_arztalep.py
arztalep-0.6.dist-info/METADATA
arztalep-0.6.dist-info/WHEEL
arztalep-0.6.dist-info/top_level.txt
arztalep-0.6.dist-info/RECORD
